ssm_ps_template/__init__.py
ssm_ps_template/__main__.py
ssm_ps_template/config.py
ssm_ps_template/discovery.py
ssm_ps_template/render.py
ssm_ps_template/ssm.py
ssm_ps_template-2.5.0.dist-info/LICENSE.txt
ssm_ps_template-2.5.0.dist-info/METADATA
ssm_ps_template-2.5.0.dist-info/WHEEL
ssm_ps_template-2.5.0.dist-info/entry_points.txt
ssm_ps_template-2.5.0.dist-info/top_level.txt
ssm_ps_template-2.5.0.dist-info/RECORD
