Metadata-Version: 2.1
Name: ssm-ps-template
Version: 2.5.0
Summary: CLI for rendering configuration templates with SSM Parameter Store as a data source
Author-email: "Gavin M. Roy" <gavinmroy@gmail.com>
License: Copyright (c) 2023 Gavin M. Roy
Project-URL: Homepage, https://github.com/gmr/ssm-ps-template
Project-URL: Bug Tracker, https://github.com/gmr/ssm-ps-template/issues
Keywords: aws,ssm,parameter store,templating
Classifier: Topic :: Software Development
Classifier: License :: OSI Approved :: BSD License
Classifier: Programming Language :: Python :: 3
Classifier: Development Status :: 5 - Production/Stable
Classifier: Environment :: Console
Classifier: Intended Audience :: Developers
Classifier: Intended Audience :: System Administrators
Classifier: Natural Language :: English
Classifier: Topic :: Text Processing
Classifier: Topic :: Utilities
Requires-Python: >=3.9
License-File: LICENSE.txt
Requires-Dist: boto3 (<2,>=1)
Requires-Dist: flatdict (<5,>=4)
Requires-Dist: jinja2 (<4,>=3)
Requires-Dist: pyyaml (<7,>=5.3.1)
Requires-Dist: toml (<1,>=0.10)
Provides-Extra: dev
Requires-Dist: build ; extra == 'dev'
Requires-Dist: coverage ; extra == 'dev'
Requires-Dist: flake8 ; extra == 'dev'
Requires-Dist: flake8-comprehensions ; extra == 'dev'
Requires-Dist: flake8-deprecated ; extra == 'dev'
Requires-Dist: flake8-import-order ; extra == 'dev'
Requires-Dist: flake8-print ; extra == 'dev'
Requires-Dist: flake8-pyproject ; extra == 'dev'
Requires-Dist: flake8-quotes ; extra == 'dev'
Requires-Dist: flake8-rst-docstrings ; extra == 'dev'
Requires-Dist: flake8-tuple ; extra == 'dev'
